voicebot_accounts/__init__.py
voicebot_accounts/admin.py
voicebot_accounts/apps.py
voicebot_accounts/context_processors.py
voicebot_accounts/forms.py
voicebot_accounts/models.py
voicebot_accounts/serializers.py
voicebot_accounts/tests.py
voicebot_accounts/urls.py
voicebot_accounts/utils.py
voicebot_accounts/views.py
voicebot_accounts/migrations/0001_initial.py
voicebot_accounts/migrations/0002_agents_user.py
voicebot_accounts/migrations/0003_agents_first_sentence.py
voicebot_accounts/migrations/0004_calllogs.py
voicebot_accounts/migrations/0005_phonenumber.py
voicebot_accounts/migrations/0006_agents_phone_number.py
voicebot_accounts/migrations/__init__.py
voicebot_accounts-0.2.dist-info/METADATA
voicebot_accounts-0.2.dist-info/WHEEL
voicebot_accounts-0.2.dist-info/top_level.txt
voicebot_accounts-0.2.dist-info/RECORD
